atlas/Snakefile
atlas/__init__.py
atlas/atlas.py
atlas/blast.py
atlas/conf.py
atlas/default_values.py
atlas/parsers.py
atlas/tables.py
atlas/template_config.yaml
atlas/utils.py
atlas/workflows.py
atlas/envs/DASTool.yaml
atlas/envs/canopy.yaml
atlas/envs/cd-hit.yaml
atlas/envs/checkm.yaml
atlas/envs/concoct.yaml
atlas/envs/dRep.yaml
atlas/envs/eggNOG.yaml
atlas/envs/maxbin.yaml
atlas/envs/metabat.yaml
atlas/envs/mmseqs.yaml
atlas/envs/optional_genome_binning.yaml
atlas/envs/prokka.yaml
atlas/envs/report.yaml
atlas/envs/required_packages.yaml
atlas/envs/sequence_utils.yaml
atlas/report/assembly_report.py
atlas/report/bin_report.py
atlas/report/qc_report.py
atlas/report/report.css
atlas/rules/annotate.snakefile
atlas/rules/assemble.snakefile
atlas/rules/binning.snakefile
atlas/rules/download.snakefile
atlas/rules/gene_annotation.snakefile
atlas/rules/genecatalog.snakefile
atlas/rules/get_fasta_of_bins.py
atlas/rules/initialize_checkm.py
atlas/rules/qc.snakefile
atlas/rules/scg_blank_diamond.rb
metagenome_atlas-2.0.0.dist-info/LICENSE.txt
metagenome_atlas-2.0.0.dist-info/METADATA
metagenome_atlas-2.0.0.dist-info/WHEEL
metagenome_atlas-2.0.0.dist-info/entry_points.txt
metagenome_atlas-2.0.0.dist-info/top_level.txt
metagenome_atlas-2.0.0.dist-info/RECORD
