Metadata-Version: 2.1
Name: metagenome-atlas
Version: 2.0.0
Summary: ATLAS - workflows for assembly, annotation, and genomic binning of metagenomic and metatranscriptomic data.
Home-page: https://github.com/metagenome-atlas/atlas
Author: Joe Brown, Silas Kieser
Author-email: brwnjm@gmail.com, silas.kieser@gmail.com
License: BSD-3
Platform: UNKNOWN
Classifier: Topic :: Scientific/Engineering :: Bio-Informatics
Requires-Dist: ruamel.yaml (==0.15.35)
